harmonic/__init__.py
harmonic/chains.py
harmonic/default-logging-config.yaml
harmonic/evidence.py
harmonic/flows.py
harmonic/logs.py
harmonic/model.py
harmonic/model_abstract.py
harmonic/model_classical.py
harmonic/model_legacy.c
harmonic/model_legacy.cpython-311-darwin.so
harmonic/model_legacy.pyx
harmonic/sddr.py
harmonic/utils.py
harmonic-1.3.0.dist-info/LICENSE.txt
harmonic-1.3.0.dist-info/LICENSE_EXT.txt
harmonic-1.3.0.dist-info/METADATA
harmonic-1.3.0.dist-info/WHEEL
harmonic-1.3.0.dist-info/top_level.txt
harmonic-1.3.0.dist-info/RECORD
