Metadata-Version: 2.1
Name: harmonic
Version: 1.3.0
Summary: Python package for efficient Bayesian evidence computation
Home-page: https://github.com/astro-informatics/harmonic
Author: Jason D. McEwen, Alicja Polanska, Christopher G. R. Wallis, Matthew A. Price, Matthew M. Docherty & Contributors
Author-email: jason.mcewen@ucl.ac.uk
License: GNU General Public License v3 (GPLv3)
Classifier: Programming Language :: Python :: 3.9
Classifier: Programming Language :: Python :: 3.10
Classifier: Programming Language :: Python :: 3.11
Classifier: Operating System :: OS Independent
Classifier: Intended Audience :: Developers
Classifier: Intended Audience :: Science/Research
License-File: LICENSE.txt
License-File: LICENSE_EXT.txt
Requires-Dist: numpy (<=1.26.4)
Requires-Dist: setuptools (==68.0.0)
Requires-Dist: wheel (==0.41.0)
Requires-Dist: cython (>=0.29.30)
Requires-Dist: ipython (>=8.4.0)
Requires-Dist: jupyter (>=1.0.0)
Requires-Dist: scikit-learn (>=1.1.1)
Requires-Dist: scipy (>=1.8.1)
Requires-Dist: colorlog (>=6.6.0)
Requires-Dist: pyyaml (>=6.0)
Requires-Dist: tqdm
Requires-Dist: jax
Requires-Dist: jaxlib
Requires-Dist: flax
Requires-Dist: distrax
Requires-Dist: cloudpickle
Requires-Dist: getdist
